CHANGELOG.txt
LICENSE.txt
MANIFEST.in
README.rst
setup.py
raumfeld/__init__.py
raumfeld.egg-info/PKG-INFO
raumfeld.egg-info/SOURCES.txt
raumfeld.egg-info/dependency_links.txt
raumfeld.egg-info/requires.txt
raumfeld.egg-info/top_level.txt