Metadata-Version: 1.1
Name: raumfeld
Version: 0.2
Summary: A pythonic library for discovering and controlling Teufel Raumfeld devices.
Home-page: https://github.com/tfeldmann/python-raumfeld
Author: Thomas Feldmann
Author-email: feldmann.thomas@gmail.com
License: MIT
Keywords: raumfeld,upnp,soap
Platform: UNKNOWN
Classifier: License :: OSI Approved :: MIT License
Classifier: Operating System :: OS Independent
Classifier: Programming Language :: Python
Classifier: Programming Language :: Python :: 2
Classifier: Programming Language :: Python :: 3
Classifier: Topic :: Software Development :: Libraries :: Python Modules
